hhj/__init__.py
hhj/__main__.py
hhj/hhj_engine.py
hhj-1.3.dist-info/licenses/LICENSE.txt
hhj-1.3.dist-info/METADATA
hhj-1.3.dist-info/WHEEL
hhj-1.3.dist-info/entry_points.txt
hhj-1.3.dist-info/top_level.txt
hhj-1.3.dist-info/RECORD
