Metadata-Version: 2.4
Name: hhj
Version: 1.3
Summary: HHJ Engine - YAML orchestrator for automated workflows
Author: NickC4p
License: DIO - See de license
License-File: LICENSE.txt
Requires-Dist: pyyaml
Requires-Dist: requests
Dynamic: license-file
